imctoolkit/__init__.py
imctoolkit/_version.py
imctoolkit/image_single_cell_data.py
imctoolkit/multichannel_image.py
imctoolkit/spatial_cell_graph.py
imctoolkit/spatial_single_cell_data.py
imctoolkit/utils.py
imctoolkit-0.1.4.dist-info/LICENSE.md
imctoolkit-0.1.4.dist-info/METADATA
imctoolkit-0.1.4.dist-info/WHEEL
imctoolkit-0.1.4.dist-info/top_level.txt
imctoolkit-0.1.4.dist-info/RECORD
