Metadata-Version: 2.1
Name: imctoolkit
Version: 0.1.4
Summary: Python package for processing segmented multi-channel images
Home-page: https://github.com/BodenmillerGroup/imctoolkit
Author: Jonas Windhager
Author-email: jonas.windhager@uzh.ch
License: MIT
Platform: UNKNOWN
Classifier: Intended Audience :: Science/Research
Classifier: License :: OSI Approved :: MIT License
Classifier: Natural Language :: English
Classifier: Operating System :: OS Independent
Classifier: Programming Language :: Python :: 3.8
Classifier: Programming Language :: Python :: 3.9
Classifier: Topic :: Scientific/Engineering :: Bio-Informatics
Classifier: Topic :: Scientific/Engineering :: Image Processing
Requires-Python: >=3.8
License-File: LICENSE.md
Requires-Dist: imctools
Requires-Dist: numpy
Requires-Dist: pandas
Requires-Dist: scikit-image
Requires-Dist: scipy
Requires-Dist: tifffile
Requires-Dist: xarray
Requires-Dist: xtiff
Provides-Extra: all
Requires-Dist: anndata ; extra == 'all'
Requires-Dist: fcswrite ; extra == 'all'
Requires-Dist: networkx ; extra == 'all'
Requires-Dist: opencv-python ; extra == 'all'
Requires-Dist: python-igraph ; extra == 'all'
